{"name":"build-javascript","namedChunkGroups":{"polyfill":{"name":"polyfill","assets":[{"name":"webpack-runtime-d69dae4864e13eafe3ca.js","size":6379},{"name":"dc6a8720040df98778fe970bf6c000a41750d3ae-3fe75017a9f98c2561b1.js","size":13536},{"name":"polyfill-bd1488b332fee73dd09a.js","size":88945}],"filteredAssets":0,"assetsSize":108860,"filteredAuxiliaryAssets":3,"auxiliaryAssetsSize":315212},"app":{"name":"app","assets":[{"name":"webpack-runtime-d69dae4864e13eafe3ca.js","size":6379},{"name":"styles.3db5d2adcac974de6e03.css","size":262758},{"name":"framework-ff6ef4b773b636f4abcc.js","size":129764},{"name":"b2e984c5-3dc4c5d695f68c134cca.js","size":16575},{"name":"dc6a8720040df98778fe970bf6c000a41750d3ae-3fe75017a9f98c2561b1.js","size":13536},{"name":"app-12f7fd83db2a0f627dda.js","size":386014}],"filteredAssets":0,"assetsSize":815026,"filteredAuxiliaryAssets":266,"auxiliaryAssetsSize":27099579},"polyfills-dom":{"name":"polyfills-dom","assets":[{"name":"polyfills-dom-fb949ba9a61dca8c5e32.js","size":18650}],"filteredAssets":0,"assetsSize":18650,"filteredAuxiliaryAssets":1,"auxiliaryAssetsSize":54289},"polyfills-core-js":{"name":"polyfills-core-js","assets":[{"name":"polyfills-core-js-639847c22e23524261c2.js","size":102992}],"filteredAssets":0,"assetsSize":102992,"filteredAuxiliaryAssets":1,"auxiliaryAssetsSize":356457},"component---src-pages-404-tsx":{"name":"component---src-pages-404-tsx","assets":[{"name":"styles.3db5d2adcac974de6e03.css","size":262758},{"name":"commons-30eda3718a0bbc6ade74.js","size":266524},{"name":"component---src-pages-404-tsx-0c5f0d54a54a14833804.js","size":997}],"filteredAssets":0,"assetsSize":530279,"filteredAuxiliaryAssets":37,"auxiliaryAssetsSize":1322964},"component---src-pages-index-tsx":{"name":"component---src-pages-index-tsx","assets":[{"name":"styles.3db5d2adcac974de6e03.css","size":262758},{"name":"commons-30eda3718a0bbc6ade74.js","size":266524},{"name":"component---src-pages-index-tsx-a924def9a6d92d2ebf34.js","size":3544}],"filteredAssets":0,"assetsSize":532826,"filteredAuxiliaryAssets":37,"auxiliaryAssetsSize":1862199},"component---src-templates-standard-index-tsx":{"name":"component---src-templates-standard-index-tsx","assets":[{"name":"styles.3db5d2adcac974de6e03.css","size":262758},{"name":"commons-30eda3718a0bbc6ade74.js","size":266524},{"name":"component---src-templates-standard-index-tsx-e15d92fb3cf39aaf1890.js","size":297844}],"filteredAssets":0,"assetsSize":827126,"filteredAuxiliaryAssets":36,"auxiliaryAssetsSize":1796665}},"assetsByChunkName":{"polyfill":["webpack-runtime-d69dae4864e13eafe3ca.js","dc6a8720040df98778fe970bf6c000a41750d3ae-3fe75017a9f98c2561b1.js","polyfill-bd1488b332fee73dd09a.js"],"app":["webpack-runtime-d69dae4864e13eafe3ca.js","styles.3db5d2adcac974de6e03.css","framework-ff6ef4b773b636f4abcc.js","b2e984c5-3dc4c5d695f68c134cca.js","dc6a8720040df98778fe970bf6c000a41750d3ae-3fe75017a9f98c2561b1.js","app-12f7fd83db2a0f627dda.js"],"polyfills-dom":["polyfills-dom-fb949ba9a61dca8c5e32.js"],"polyfills-core-js":["polyfills-core-js-639847c22e23524261c2.js"],"component---src-pages-404-tsx":["styles.3db5d2adcac974de6e03.css","commons-30eda3718a0bbc6ade74.js","component---src-pages-404-tsx-0c5f0d54a54a14833804.js"],"component---src-pages-index-tsx":["styles.3db5d2adcac974de6e03.css","commons-30eda3718a0bbc6ade74.js","component---src-pages-index-tsx-a924def9a6d92d2ebf34.js"],"component---src-templates-standard-index-tsx":["styles.3db5d2adcac974de6e03.css","commons-30eda3718a0bbc6ade74.js","component---src-templates-standard-index-tsx-e15d92fb3cf39aaf1890.js"]},"childAssetsByChunkName":{}}